{
  "words": [
    {
      "german": "die Beute",
      "english": "prey",
      "difficulty": "medium"
    },
    {
      "german": "das Raubtier",
      "english": "predator",
      "difficulty": "medium"
    },
    {
      "german": "das Ereignis",
      "english": "event",
      "difficulty": "medium"
    },
    {
      "german": "die Bedingung",
      "english": "condition",
      "difficulty": "medium"
    },
    {
      "german": "allerdings",
      "english": "however",
      "difficulty": "medium"
    },
    {
      "german": "der Lebensraum",
      "english": "habitat",
      "difficulty": "medium"
    },
    {
      "german": "die Überreste",
      "english": "remains",
      "difficulty": "medium"
    },
    {
      "german": "fern",
      "english": "remote",
      "difficulty": "medium"
    },
    {
      "german": "böse",
      "english": "evil",
      "difficulty": "medium"
    },
    {
      "german": "zutaten",
      "english": "ingredients",
      "difficulty": "medium"
    },
    {
      "german": "der Zwiespalt",
      "english": "inner conflict",
      "difficulty": "hard"
    },
    {
      "german": "die Befangenheit",
      "english": "bias, self-consciousness",
      "difficulty": "hard"
    },
    {
      "german": "die Raffinesse",
      "english": "sophistication, cunning",
      "difficulty": "hard"
    },
    {
      "german": "die Verworrenheit",
      "english": "confusion, entanglement",
      "difficulty": "hard"
    },
    {
      "german": "der Argwohn",
      "english": "suspicion",
      "difficulty": "hard"
    },
    {
      "german": "die Unzulänglichkeit",
      "english": "shortcoming, inadequacy",
      "difficulty": "hard"
    },
    {
      "german": "die Abgeschiedenheit",
      "english": "seclusion, isolation",
      "difficulty": "hard"
    },
    {
      "german": "die Entbehrung",
      "english": "privation, hardship",
      "difficulty": "hard"
    },
    {
      "german": "die Gewissenhaftigkeit",
      "english": "conscientiousness",
      "difficulty": "hard"
    },
    {
      "german": "der Hochmut",
      "english": "arrogance, haughtiness",
      "difficulty": "hard"
    },
    {
      "german": "der Makel",
      "english": "blemish, flaw",
      "difficulty": "hard"
    },
    {
      "german": "die Heimtücke",
      "english": "treachery, insidiousness",
      "difficulty": "hard"
    },
    {
      "german": "die Verstörtheit",
      "english": "bewilderment, dismay",
      "difficulty": "hard"
    },
    {
      "german": "die Zerknirschung",
      "english": "remorse, contrition",
      "difficulty": "hard"
    },
    {
      "german": "die Fügung",
      "english": "providence, coincidence",
      "difficulty": "hard"
    },
    {
      "german": "die Bredouille",
      "english": "predicament (colloquial)",
      "difficulty": "hard"
    },
    {
      "german": "die Arglist",
      "english": "deceit, guile",
      "difficulty": "hard"
    },
    {
      "german": "überdrüssig",
      "english": "weary, fed up with",
      "difficulty": "hard"
    },
    {
      "german": "verworren",
      "english": "confused, tangled",
      "difficulty": "hard"
    },
    {
      "german": "verdrießlich",
      "english": "sullen, morose",
      "difficulty": "hard"
    },
    {
      "german": "ungezügelt",
      "english": "unrestrained, rampant",
      "difficulty": "hard"
    },
    {
      "german": "schroff",
      "english": "abrupt, harsh",
      "difficulty": "hard"
    },
    {
      "german": "tückisch",
      "english": "treacherous, insidious",
      "difficulty": "hard"
    },
    {
      "german": "argwöhnisch",
      "english": "suspicious, distrustful",
      "difficulty": "hard"
    },
    {
      "german": "weitschweifig",
      "english": "long-winded, verbose",
      "difficulty": "hard"
    },
    {
      "german": "abgründig",
      "english": "profound, unfathomable",
      "difficulty": "hard"
    },
    {
      "german": "unverhohlen",
      "english": "unconcealed, blatant",
      "difficulty": "hard"
    },
    {
      "german": "standhaft",
      "english": "steadfast, resilient",
      "difficulty": "hard"
    },
    {
      "german": "unerschwinglich",
      "english": "prohibitively expensive",
      "difficulty": "hard"
    },
    {
      "german": "schneidig",
      "english": "dashing, spirited",
      "difficulty": "hard"
    }
  ]
}